beekeeping/__init__.py
beekeeping/app.py
beekeeping/utils.py
beekeeping/callbacks/__init__.py
beekeeping/callbacks/home.py
beekeeping/callbacks/metadata.py
beekeeping/pages/home.py
beekeeping/pages/metadata.py
beekeeping-0.3.4.dist-info/licenses/LICENSE
beekeeping-0.3.4.dist-info/METADATA
beekeeping-0.3.4.dist-info/WHEEL
beekeeping-0.3.4.dist-info/entry_points.txt
beekeeping-0.3.4.dist-info/top_level.txt
beekeeping-0.3.4.dist-info/RECORD
