Metadata-Version: 2.4
Name: beekeeping
Version: 0.3.4
Summary: Manage video metadata for animal behaviour experiments
Author-email: Sofia Miñano <s.minano@ucl.ac.uk>, Nikoloz Sirmpilatze <niko.sirbiladze@gmail.com>, Sam Cunliffe <s.cunliffe@ucl.ac.uk>, Adam Tyson <code@adamltyson.com>
License: BSD-3-Clause
Project-URL: Homepage, https://github.com/neuroinformatics-unit/beekeeping
Project-URL: Bug tracker, https://github.com/neuroinformatics-unit/beekeeping/issues
Project-URL: Source code, https://github.com/neuroinformatics-unit/beekeeping
Project-URL: User support, https://github.com/neuroinformatics-unit/beekeeping/issues
Classifier: Development Status :: 2 - Pre-Alpha
Classifier: Programming Language :: Python
Classifier: Programming Language :: Python :: 3
Classifier: Programming Language :: Python :: 3.11
Classifier: Programming Language :: Python :: 3.12
Classifier: Programming Language :: Python :: 3.13
Classifier: Operating System :: OS Independent
Classifier: License :: OSI Approved :: BSD License
Requires-Python: >=3.11.0
License-File: LICENSE
Requires-Dist: numpy
Requires-Dist: pandas
Requires-Dist: dash
Requires-Dist: dash-bootstrap-components
Requires-Dist: PyYAML
Requires-Dist: openpyxl
Provides-Extra: dev
Requires-Dist: pytest; extra == "dev"
Requires-Dist: pytest-cov; extra == "dev"
Requires-Dist: coverage; extra == "dev"
Requires-Dist: dash[testing]; extra == "dev"
Requires-Dist: tox; extra == "dev"
Requires-Dist: ruff; extra == "dev"
Requires-Dist: mypy; extra == "dev"
Requires-Dist: pre-commit; extra == "dev"
Requires-Dist: setuptools-scm; extra == "dev"
Requires-Dist: types-PyYAML; extra == "dev"
Requires-Dist: pandas-stubs; extra == "dev"
Dynamic: license-file
